mdsthin/__init__.py
mdsthin/connection.py
mdsthin/descriptors.py
mdsthin/exceptions.py
mdsthin/functions.py
mdsthin/message.py
mdsthin/MDSplus/__init__.py
mdsthin/ext/GetManyMany.py
mdsthin/ext/__init__.py
mdsthin/ext/tree.py
mdsthin/internals/CvtConvertFloat.py
mdsthin/internals/classdef.py
mdsthin/internals/dtypedef.py
mdsthin/internals/mdsdescrip.py
mdsthin/internals/opcbuiltins.py
mdsthin/internals/usagedef.py
mdsthin/mdstcl/__main__.py
mdsthin/tdic/__main__.py
mdsthin/test/__init__.py
mdsthin/test/__main__.py
mdsthin/test/cmod_test.py
mdsthin/test/connection_test.py
mdsthin/test/descriptors_test.py
mdsthin/test/exceptions_test.py
mdsthin/test/run.py
mdsthin/test/serialize_test.py
mdsthin/test/write_test.py
mdsthin-1.6.0.dist-info/licenses/LICENSE
mdsthin-1.6.0.dist-info/METADATA
mdsthin-1.6.0.dist-info/WHEEL
mdsthin-1.6.0.dist-info/top_level.txt
mdsthin-1.6.0.dist-info/RECORD
