Metadata-Version: 2.4
Name: mdsthin
Version: 1.6.0
Summary: MDSplus Thin-Client implemented in pure python
Author-email: Stephen Lane-Walsh <slwalsh@psfc.mit.edu>
License: 
Project-URL: Homepage, https://github.com/MDSplus/mdsthin
Project-URL: Bug Reports, https://github.com/MDSplus/mdsthin/issues
Project-URL: Source, https://github.com/MDSplus/mdsthin/
Requires-Python: >=3.7
License-File: LICENSE
Requires-Dist: numpy
Dynamic: license-file
